patternengine/__init__.py
patternengine/bullet.py
patternengine/bullets.py
patternengine/compsys.py
patternengine/engine.py
patternengine/example.py
patternengine/peglm.py
patternengine/poms.py
patternengine/demos/00.py
patternengine/demos/01.py
patternengine/demos/02.py
patternengine/demos/03.py
patternengine/demos/04.py
patternengine/demos/05.py
patternengine/demos/06.py
patternengine/demos/__init__.py
patternengine/tutorial/__init__.py
patternengine/tutorial/tut00.py
patternengine/tutorial/tut01.py
patternengine/tutorial/tut02.py
patternengine/tutorial/tut03.py
patternengine/tutorial/tut04.py
patternengine/tutorial/tut05.py
patternengine/tutorial/tut06.py
patternengine/tutorial/tut07.py
patternengine/tutorial/tut08.py
patternengine/tutorial/tut08a.py
patternengine-0.0.6.dist-info/LICENSE
patternengine-0.0.6.dist-info/METADATA
patternengine-0.0.6.dist-info/WHEEL
patternengine-0.0.6.dist-info/entry_points.txt
patternengine-0.0.6.dist-info/top_level.txt
patternengine-0.0.6.dist-info/RECORD
