Metadata-Version: 2.1
Name: patternengine
Version: 0.0.6
Summary: patternengine
Author-email: Michael Lamertz <michael.lamertz@gmail.com>
Project-URL: homepage, https://github.com/dickerdackel/patternengine
Project-URL: bugtracker, https://github.com/DickerDackel/patternengine/issues
Classifier: Development Status :: 3 - Alpha
Classifier: Intended Audience :: Developers
Classifier: License :: OSI Approved :: MIT License
Classifier: Topic :: Games/Entertainment
Classifier: Topic :: Software Development :: Libraries :: pygame
License-File: LICENSE
Requires-Dist: pygame-ce
Requires-Dist: pgcooldown
Requires-Dist: rpeasings
Requires-Dist: pyglm
